brary/__init__.py
brary/bots.py
brary/economy.py
brary/essentials.py
brary/location.py
brary/space.py
brary-1.dist-info/licenses/LICENSE
brary-1.dist-info/METADATA
brary-1.dist-info/WHEEL
brary-1.dist-info/top_level.txt
brary-1.dist-info/RECORD
